alerta/__init__.py
alerta/app.py
alerta/app.wsgi
alerta/build.py
alerta/commands.py
alerta/dev.py
alerta/exceptions.py
alerta/settings.py
alerta/tasks.py
alerta/version.py
alerta/auth/__init__.py
alerta/auth/basic.py
alerta/auth/basic_ldap.py
alerta/auth/decorators.py
alerta/auth/github.py
alerta/auth/hmac.py
alerta/auth/logout.py
alerta/auth/oidc.py
alerta/auth/saml.py
alerta/auth/userinfo.py
alerta/auth/utils.py
alerta/database/__init__.py
alerta/database/base.py
alerta/database/backends/__init__.py
alerta/database/backends/mongodb/__init__.py
alerta/database/backends/mongodb/base.py
alerta/database/backends/mongodb/queryparser.py
alerta/database/backends/mongodb/utils.py
alerta/database/backends/postgres/__init__.py
alerta/database/backends/postgres/base.py
alerta/database/backends/postgres/queryparser.py
alerta/database/backends/postgres/utils.py
alerta/management/__init__.py
alerta/management/views.py
alerta/models/__init__.py
alerta/models/alert.py
alerta/models/blackout.py
alerta/models/customer.py
alerta/models/enums.py
alerta/models/group.py
alerta/models/heartbeat.py
alerta/models/history.py
alerta/models/key.py
alerta/models/metrics.py
alerta/models/note.py
alerta/models/permission.py
alerta/models/switch.py
alerta/models/token.py
alerta/models/user.py
alerta/models/alarms/__init__.py
alerta/models/alarms/alerta.py
alerta/models/alarms/isa_18_2.py
alerta/plugins/__init__.py
alerta/plugins/acked_by.py
alerta/plugins/blackout.py
alerta/plugins/forwarder.py
alerta/plugins/heartbeat.py
alerta/plugins/reject.py
alerta/plugins/remote_ip.py
alerta/sql/schema.sql
alerta/static/embed.js
alerta/templates/index.html
alerta/templates/auth/saml2.html
alerta/templates/management/index.html
alerta/templates/management/switchboard.html
alerta/templates/oembed/counts.html
alerta/utils/__init__.py
alerta/utils/api.py
alerta/utils/audit.py
alerta/utils/client.py
alerta/utils/collections.py
alerta/utils/config.py
alerta/utils/format.py
alerta/utils/hooks.py
alerta_server_shakti-8.0.3.dist-info/LICENSE
alerta_server_shakti-8.0.3.dist-info/METADATA
alerta_server_shakti-8.0.3.dist-info/NOTICE
alerta_server_shakti-8.0.3.dist-info/WHEEL
alerta_server_shakti-8.0.3.dist-info/entry_points.txt
alerta_server_shakti-8.0.3.dist-info/top_level.txt
alerta_server_shakti-8.0.3.dist-info/RECORD
