Metadata-Version: 2.1
Name: alerta-server-shakti
Version: 8.0.3
Summary: Alerta server WSGI application
Home-page: https://github.com/guardian/alerta
Author: Nick Satterly
Author-email: nick.satterly@gmail.com
License: Apache License 2.0
Keywords: alert monitoring system wsgi application api
Platform: UNKNOWN
Classifier: Development Status :: 5 - Production/Stable
Classifier: Environment :: Web Environment
Classifier: Environment :: Plugins
Classifier: Framework :: Flask
Classifier: Intended Audience :: Information Technology
Classifier: Intended Audience :: System Administrators
Classifier: Intended Audience :: Telecommunications Industry
Classifier: License :: OSI Approved :: Apache Software License
Classifier: Programming Language :: Python :: 3.8
Classifier: Programming Language :: Python :: 3.7
Classifier: Programming Language :: Python :: 3.6
Classifier: Topic :: System :: Monitoring
Requires-Python: >=3.6
Requires-Dist: bcrypt
Requires-Dist: cryptography
Requires-Dist: Flask (>=0.10.1)
Requires-Dist: Flask-Compress (>=1.4.0)
Requires-Dist: Flask-Cors (>=3.0.2)
Requires-Dist: mohawk
Requires-Dist: PyJWT
Requires-Dist: pymongo (>=3.6)
Requires-Dist: pyparsing
Requires-Dist: python-dateutil
Requires-Dist: pytz
Requires-Dist: pyyaml
Requires-Dist: requests
Requires-Dist: requests-hawk
Requires-Dist: sentry-sdk[flask] (>=0.10.2)
Provides-Extra: mongodb
Requires-Dist: pymongo (>=3.0) ; extra == 'mongodb'
Provides-Extra: postgres
Requires-Dist: psycopg2 ; extra == 'postgres'
